{
  "type": "farmersdelight:cutting",
  "ingredients": [
    {
      "item": "minecraft:gravel"
    }
  ],
  "result": [
    {
      "item": "minecraft:gravel"
    },
    {
      "chance": 0.1,
      "item": "minecraft:flint"
    }
  ],
  "tool": [
    {
      "item": "minecraft:wooden_shovel"
    },
    {
      "item": "minecraft:stone_shovel"
    },
    {
      "item": "minecraft:golden_shovel"
    },
    {
      "item": "minecraft:iron_shovel"
    },
    {
      "item": "minecraft:diamond_shovel"
    },
    {
      "item": "minecraft:netherite_shovel"
    }
  ]
}