{
  "variants": {
    "facing=north,open=false": {
      "model": "farmersdelight:block/warped_pantry"
    },
    "facing=south,open=false": {
      "model": "farmersdelight:block/warped_pantry",
      "y": 180
    },
    "facing=west,open=false": {
      "model": "farmersdelight:block/warped_pantry",
      "y": 270
    },
    "facing=east,open=false": {
      "model": "farmersdelight:block/warped_pantry",
      "y": 90
    },
    "facing=north,open=true": {
      "model": "farmersdelight:block/warped_pantry_open"
    },
    "facing=south,open=true": {
      "model": "farmersdelight:block/warped_pantry_open",
      "y": 180
    },
    "facing=west,open=true": {
      "model": "farmersdelight:block/warped_pantry_open",
      "y": 270
    },
    "facing=east,open=true": {
      "model": "farmersdelight:block/warped_pantry_open",
      "y": 90
    }
  }
}