{
  "type": "farmersdelight:cooking",
  "ingredients": [
    {
      "item": "minecraft:baked_potato"
    },
    [
      {
        "item": "minecraft:rabbit"
      },
      {
        "item": "minecraft:cooked_rabbit"
      }
    ],
    {
      "item": "minecraft:carrot"
    },
    [
      {
        "item": "minecraft:brown_mushroom"
      },
      {
        "item": "minecraft:red_mushroom"
      }
    ]
  ],
  "result": {
    "item": "minecraft:rabbit_stew"
  },
  "container": {
    "item": "minecraft:bowl"
  },
  "experience": 0.35,
  "cookingtime": 200
}