{
  "parent": "minecraft:recipes/root",
  "rewards": {
    "recipes": [
      "farmersdelight:cooking/dog_food"
    ]
  },
  "criteria": {
    "has_rotten_flesh": {
      "trigger": "minecraft:inventory_changed",
      "conditions": {
        "items": [
          {
            "items": [
              "minecraft:rotten_flesh"
            ]
          }
        ]
      }
    },
    "has_the_recipe": {
      "trigger": "minecraft:recipe_unlocked",
      "conditions": {
        "recipe": "farmersdelight:cooking/dog_food"
      }
    }
  },
  "requirements": [
    [
      "has_rotten_flesh",
      "has_the_recipe"
    ]
  ]
}